audiobook/__init__.py
audiobook/api.py
audiobook/cli.py
audiobook/config.py
audiobook/generate.py
audiobook/servant.py
audiobook_rss-0.1.3.dist-info/METADATA
audiobook_rss-0.1.3.dist-info/WHEEL
audiobook_rss-0.1.3.dist-info/entry_points.txt
audiobook_rss-0.1.3.dist-info/top_level.txt
audiobook_rss-0.1.3.dist-info/RECORD
